pcdviewer/PCDViewer.py
pcdviewer/PCDViewerWidget.py
pcdviewer/__init__.py
PCDViewer-1.0.0.dist-info/LICENSE
PCDViewer-1.0.0.dist-info/METADATA
PCDViewer-1.0.0.dist-info/WHEEL
PCDViewer-1.0.0.dist-info/entry_points.txt
PCDViewer-1.0.0.dist-info/top_level.txt
PCDViewer-1.0.0.dist-info/RECORD
